vf_config_model/__init__.py
vf_config_model/client_config_models.py
vf_config_model-1.0.0.dist-info/licenses/LICENSE
vf_config_model-1.0.0.dist-info/METADATA
vf_config_model-1.0.0.dist-info/WHEEL
vf_config_model-1.0.0.dist-info/top_level.txt
vf_config_model-1.0.0.dist-info/RECORD
