Metadata-Version: 2.4
Name: vf-config-model
Version: 1.0.0
Summary: Shared client configuration models for Verbaflo
Author-email: Raj Kamal <raj.kamal@verbaflo.com>
License-Expression: MIT
Project-URL: Homepage, https://github.com/verbaflo/config-model
Project-URL: Repository, https://github.com/verbaflo/config-model.git
Project-URL: Documentation, https://github.com/verbaflo/config-model#readme
Requires-Python: >=3.7
License-File: LICENSE
Requires-Dist: pydantic>=2.0.0
Requires-Dist: typing-extensions>=4.0.0
Dynamic: license-file
